wemake_python_styleguide/__init__.py
wemake_python_styleguide/checker.py
wemake_python_styleguide/compat/__init__.py
wemake_python_styleguide/compat/aliases.py
wemake_python_styleguide/compat/constants.py
wemake_python_styleguide/compat/functions.py
wemake_python_styleguide/compat/nodes.py
wemake_python_styleguide/compat/packaging.py
wemake_python_styleguide/compat/routing.py
wemake_python_styleguide/compat/types.py
wemake_python_styleguide/constants.py
wemake_python_styleguide/formatter.py
wemake_python_styleguide/logic/__init__.py
wemake_python_styleguide/logic/arguments/__init__.py
wemake_python_styleguide/logic/arguments/call_args.py
wemake_python_styleguide/logic/arguments/function_args.py
wemake_python_styleguide/logic/arguments/super_args.py
wemake_python_styleguide/logic/complexity/__init__.py
wemake_python_styleguide/logic/complexity/annotations.py
wemake_python_styleguide/logic/complexity/cognitive.py
wemake_python_styleguide/logic/complexity/functions.py
wemake_python_styleguide/logic/complexity/overuses.py
wemake_python_styleguide/logic/filenames.py
wemake_python_styleguide/logic/naming/__init__.py
wemake_python_styleguide/logic/naming/access.py
wemake_python_styleguide/logic/naming/alphabet.py
wemake_python_styleguide/logic/naming/blacklists.py
wemake_python_styleguide/logic/naming/builtins.py
wemake_python_styleguide/logic/naming/constants.py
wemake_python_styleguide/logic/naming/logical.py
wemake_python_styleguide/logic/naming/name_nodes.py
wemake_python_styleguide/logic/nodes.py
wemake_python_styleguide/logic/safe_eval.py
wemake_python_styleguide/logic/scopes/__init__.py
wemake_python_styleguide/logic/scopes/defs.py
wemake_python_styleguide/logic/scopes/predicates.py
wemake_python_styleguide/logic/source.py
wemake_python_styleguide/logic/system.py
wemake_python_styleguide/logic/tokens/__init__.py
wemake_python_styleguide/logic/tokens/brackets.py
wemake_python_styleguide/logic/tokens/comprehensions.py
wps_light-0.16.1.dist-info/entry_points.txt
wps_light-0.16.1.dist-info/LICENSE
wps_light-0.16.1.dist-info/WHEEL
wps_light-0.16.1.dist-info/METADATA
wps_light-0.16.1.dist-info/RECORD
