Metadata-Version: 2.1
Name: wps-light
Version: 0.16.1
Summary: The strictest and most opinionated python linter ever (lighter fork).
Home-page: https://github.com/pawamoy/wps-light
License: MIT
Keywords: flake8,flake8-plugin,flake8-formatter,linter,wemake.services,styleguide,code quality,pycqa
Author: Timothée Mazzucotelli
Author-email: pawamoy@pm.me
Requires-Python: >=3.6.2,<4
Classifier: Development Status :: 4 - Beta
Classifier: Environment :: Console
Classifier: Framework :: Flake8
Classifier: Intended Audience :: Developers
Classifier: License :: OSI Approved :: MIT License
Classifier: Operating System :: OS Independent
Classifier: Programming Language :: Python :: 3
Classifier: Programming Language :: Python :: 3.10
Classifier: Programming Language :: Python :: 3.7
Classifier: Programming Language :: Python :: 3.8
Classifier: Programming Language :: Python :: 3.9
Classifier: Topic :: Software Development :: Libraries :: Python Modules
Classifier: Topic :: Software Development :: Quality Assurance
Requires-Dist: astor (>=0.8)
Requires-Dist: attrs
Requires-Dist: flake8 (>=3.7)
Requires-Dist: flake8-polyfill (>=1.0.2)
Requires-Dist: importlib-metadata; python_version < "3.8"
Requires-Dist: pygments (>=2.4)
Requires-Dist: typing_extensions (>=3.6)
Project-URL: Funding, https://opencollective.com/wemake-python-styleguide
Project-URL: Repository, https://github.com/pawamoy/wps-light
